dialoguefactory/__init__.py
dialoguefactory/dialogue_generator.py
dialoguefactory/environment/__init__.py
dialoguefactory/environment/actions.py
dialoguefactory/environment/descriptions.py
dialoguefactory/environment/entities.py
dialoguefactory/environment/helpers.py
dialoguefactory/environments/__init__.py
dialoguefactory/environments/builders.py
dialoguefactory/environments/easy.py
dialoguefactory/environments/hard.py
dialoguefactory/environments/path_helpers.py
dialoguefactory/environments/world.py
dialoguefactory/generation/__init__.py
dialoguefactory/generation/dialogue.py
dialoguefactory/generation/file_list_db.py
dialoguefactory/generation/goal_generators.py
dialoguefactory/generation/helpers.py
dialoguefactory/generation/mappers_database.py
dialoguefactory/generation/param_generators.py
dialoguefactory/generation/templates.py
dialoguefactory/language/__init__.py
dialoguefactory/language/components.py
dialoguefactory/language/desc_mappers.py
dialoguefactory/language/describers.py
dialoguefactory/language/helpers.py
dialoguefactory/language/phrases.py
dialoguefactory/language/queries.py
dialoguefactory/language/sentences.py
dialoguefactory/language/words.py
dialoguefactory/policies/__init__.py
dialoguefactory/policies/agent_policies.py
dialoguefactory/policies/base_policies.py
dialoguefactory/policies/env_policies.py
dialoguefactory/policies/goals.py
dialoguefactory/policies/policies_helpers.py
dialoguefactory/policies/user_policies.py
dialoguefactory/state/__init__.py
dialoguefactory/state/kn_checkers.py
dialoguefactory/state/kn_helpers.py
dialoguefactory/state/kn_parsers.py
dialoguefactory/state/kn_updaters.py
dialoguefactory/state/knowledge_base.py
dialoguefactory/trainers/__init__.py
dialoguefactory/trainers/arch.py
dialoguefactory/trainers/baseline.py
dialoguefactory/trainers/evaluation.py
dialoguefactory/trainers/serializers.py
dialoguefactory/trainers/vocab.py
dialoguefactory-1.0.0.dist-info/METADATA
dialoguefactory-1.0.0.dist-info/WHEEL
dialoguefactory-1.0.0.dist-info/licenses/LICENSE.md
dialoguefactory-1.0.0.dist-info/RECORD
