Metadata-Version: 2.3
Name: dialoguefactory
Version: 1.0.0
Summary: A library for automatically generating dialogues grounded in a textual environment.
Project-URL: Homepage, https://github.com/smartinovski/dialoguefactory
Project-URL: Issues, https://github.com/smartinovski/dialoguefactory/issues
Project-URL: Contribute, https://github.com/smartinovski/dialoguefactory#contribute
Project-URL: Support Us, https://github.com/smartinovski/dialoguefactory#support-us
Author-email: Stefan Martinovski <dialoguefactory@outlook.com>
License-File: LICENSE.md
Classifier: License :: OSI Approved :: MIT License
Classifier: Operating System :: OS Independent
Classifier: Programming Language :: Python :: 3
Requires-Python: >=3.8
Requires-Dist: dijkstar
Requires-Dist: file-read-backwards
Requires-Dist: ipywidgets
Requires-Dist: notebook
Requires-Dist: pyinflect
Requires-Dist: spacy
Requires-Dist: tqdm
